setup.py
pycept/__init__.py
pycept/cept.py
pycept/version.py
pycept.egg-info/PKG-INFO
pycept.egg-info/SOURCES.txt
pycept.egg-info/dependency_links.txt
pycept.egg-info/requires.txt
pycept.egg-info/top_level.txt