Metadata-Version: 1.1
Name: pycept
Version: 1.0.0
Summary: Python client for CEPT API
Home-page: http://github.com/numenta/pycept
Author: Matthew Taylor
Author-email: matt@numenta.org
License: MIT
Download-URL: https://pypi.python.org/packages/source/g/pycept/pycept-1.0.0.tar.gz
Keywords: sdr,nlp,cept
Platform: UNKNOWN
Classifier: Development Status :: 1 - Planning
Classifier: Environment :: Console
Classifier: Intended Audience :: Developers
Classifier: License :: OSI Approved :: MIT License
Classifier: Natural Language :: English
Classifier: Operating System :: OS Independent
Classifier: Programming Language :: Python
